certbot_dns_tencentcloud/__init__.py
certbot_dns_tencentcloud/certbot_tencentcloud_plugins.py
certbot_dns_tencentcloud-2.0.2.dist-info/LICENSE
certbot_dns_tencentcloud-2.0.2.dist-info/METADATA
certbot_dns_tencentcloud-2.0.2.dist-info/WHEEL
certbot_dns_tencentcloud-2.0.2.dist-info/entry_points.txt
certbot_dns_tencentcloud-2.0.2.dist-info/top_level.txt
certbot_dns_tencentcloud-2.0.2.dist-info/RECORD
