Metadata-Version: 2.1
Name: certbot-dns-tencentcloud
Version: 2.0.2
Summary: Tencent Cloud DNS Authenticator plugin for Certbot
Home-page: https://github.com/frefreak/certbot-dns-tencentcloud
Author: Xiangyu Zhu
Author-email: carsonzhu@tencent.com
Classifier: Environment :: Plugins
Classifier: Intended Audience :: System Administrators
Classifier: Operating System :: POSIX :: Linux
Classifier: Programming Language :: Python
Classifier: Programming Language :: Python :: 3.7
Classifier: Programming Language :: Python :: 3.8
Classifier: Programming Language :: Python :: 3.9
Classifier: Programming Language :: Python :: 3.10
Classifier: Programming Language :: Python :: 3.11
Classifier: Topic :: Internet :: WWW/HTTP
Classifier: Topic :: Security
Classifier: Topic :: System :: Installation/Setup
Classifier: Topic :: System :: Networking
Classifier: Topic :: System :: Systems Administration
Classifier: Topic :: Utilities
License-File: LICENSE
Requires-Dist: certbot (>=1.18.0)
